gitlab_languages/__main__.py
gitlab_languages/gitlab_languages.py
gitlab_languages-2.4.0.dist-info/LICENSE
gitlab_languages-2.4.0.dist-info/METADATA
gitlab_languages-2.4.0.dist-info/WHEEL
gitlab_languages-2.4.0.dist-info/entry_points.txt
gitlab_languages-2.4.0.dist-info/RECORD
