Metadata-Version: 2.1
Name: gitlab-languages
Version: 2.4.0
Summary: Utility to generate a Prometheus data source from programming languages inside GitLab repositores
Home-page: https://github.com/max-wittig/gitlab-languages
License: MIT
Keywords: gitlab,languages,api,python-gitlab,prometheus,metrics
Author: Max Wittig
Requires-Python: >=3.10,<4.0
Classifier: Development Status :: 5 - Production/Stable
Classifier: Environment :: Console
Classifier: Intended Audience :: Developers
Classifier: License :: OSI Approved :: MIT License
Classifier: Operating System :: OS Independent
Classifier: Programming Language :: Python :: 3
Classifier: Programming Language :: Python :: 3.10
Classifier: Programming Language :: Python :: 3.11
Classifier: Programming Language :: Python :: 3.12
Classifier: Topic :: Software Development
Classifier: Topic :: Utilities
Requires-Dist: maya (>=0.6.1,<0.7.0)
Requires-Dist: prometheus-client (>=0.15.0,<0.16.0)
Requires-Dist: python-gitlab (>=4.5.0,<5.0.0)
Project-URL: Repository, https://github.com/max-wittig/gitlab-languages
